{
  "meta": {
    "seed": 9461818050,
    "dateRun": "2025-12-17T10:03:19.437Z",
    "duration": "24 Hours"
  },
  "summary": {
    "totalAgents": 500000,
    "totalCasualties": 0,
    "exposure": {
      "protocolA_OutdoorMins": 70473970,
      "protocolB_OutdoorMins": 72863110
    }
  },
  "stats": {
    "protocolA": {
      "outdoorsMinutes": 70473970,
      "struck": 0,
      "count": 250000
    },
    "protocolB": {
      "outdoorsMinutes": 72863110,
      "struck": 0,
      "count": 250000
    }
  }
}