{
  "meta": {
    "seed": 9420884065,
    "dateRun": "2025-12-17T10:05:02.240Z",
    "duration": "24 Hours"
  },
  "summary": {
    "totalAgents": 500000,
    "totalCasualties": 0,
    "exposure": {
      "protocolA_OutdoorMins": 70839810,
      "protocolB_OutdoorMins": 72873805
    }
  },
  "stats": {
    "protocolA": {
      "outdoorsMinutes": 70839810,
      "struck": 0,
      "count": 250000
    },
    "protocolB": {
      "outdoorsMinutes": 72873805,
      "struck": 0,
      "count": 250000
    }
  }
}