{
  "meta": {
    "seed": 8881489739,
    "dateRun": "2025-12-16T18:59:17.459Z",
    "duration": "24 Hours"
  },
  "summary": {
    "totalAgents": 500000,
    "totalCasualties": 0,
    "exposure": {
      "protocolA_OutdoorMins": 70955205,
      "protocolB_OutdoorMins": 72906500
    }
  },
  "stats": {
    "protocolA": {
      "outdoorsMinutes": 70955205,
      "struck": 0,
      "count": 250000
    },
    "protocolB": {
      "outdoorsMinutes": 72906500,
      "struck": 0,
      "count": 250000
    }
  }
}