{
  "meta": {
    "seed": 2512604944,
    "dateRun": "2025-12-17T09:59:51.329Z",
    "duration": "24 Hours"
  },
  "summary": {
    "totalAgents": 500000,
    "totalCasualties": 0,
    "exposure": {
      "protocolA_OutdoorMins": 71034585,
      "protocolB_OutdoorMins": 72910490
    }
  },
  "stats": {
    "protocolA": {
      "outdoorsMinutes": 71034585,
      "struck": 0,
      "count": 250000
    },
    "protocolB": {
      "outdoorsMinutes": 72910490,
      "struck": 0,
      "count": 250000
    }
  }
}