{
  "meta": {
    "seed": 1601143606,
    "dateRun": "2025-12-17T04:45:59.456Z",
    "duration": "24 Hours"
  },
  "summary": {
    "totalAgents": 500000,
    "totalCasualties": 0,
    "exposure": {
      "protocolA_OutdoorMins": 70394790,
      "protocolB_OutdoorMins": 72865405
    }
  },
  "stats": {
    "protocolA": {
      "outdoorsMinutes": 70394790,
      "struck": 0,
      "count": 250000
    },
    "protocolB": {
      "outdoorsMinutes": 72865405,
      "struck": 0,
      "count": 250000
    }
  }
}