{
  "meta": {
    "seed": 2780232236,
    "dateRun": "2025-12-17T09:04:20.470Z",
    "duration": "24 Hours"
  },
  "summary": {
    "totalAgents": 500000,
    "totalCasualties": 0,
    "exposure": {
      "protocolA_OutdoorMins": 70600475,
      "protocolB_OutdoorMins": 72913500
    }
  },
  "stats": {
    "protocolA": {
      "outdoorsMinutes": 70600475,
      "struck": 0,
      "count": 250000
    },
    "protocolB": {
      "outdoorsMinutes": 72913500,
      "struck": 0,
      "count": 250000
    }
  }
}