{
  "meta": {
    "seed": 1509338697,
    "dateRun": "2025-12-17T05:26:23.155Z",
    "duration": "24 Hours"
  },
  "summary": {
    "totalAgents": 500000,
    "totalCasualties": 0,
    "exposure": {
      "protocolA_OutdoorMins": 70700990,
      "protocolB_OutdoorMins": 72886925
    }
  },
  "stats": {
    "protocolA": {
      "outdoorsMinutes": 70700990,
      "struck": 0,
      "count": 250000
    },
    "protocolB": {
      "outdoorsMinutes": 72886925,
      "struck": 0,
      "count": 250000
    }
  }
}